bog/__init__.py
bog/main.py
bog-0.0.2.dist-info/LICENSE.md
bog-0.0.2.dist-info/METADATA
bog-0.0.2.dist-info/WHEEL
bog-0.0.2.dist-info/entry_points.txt
bog-0.0.2.dist-info/top_level.txt
bog-0.0.2.dist-info/RECORD
