Metadata-Version: 2.1
Name: bog
Version: 0.0.2
Summary: A visceral exploration of utility functions.
Home-page: https://github.com/DailyDreaming/bog
Download-URL: https://github.com/DailyDreaming/bog
Author: Lon
Author-email: lblauvel@ucsc.edu
License: Apache 2.0
Platform: Posix
Classifier: Intended Audience :: Developers
Classifier: License :: OSI Approved :: Apache Software License
Classifier: Operating System :: POSIX
Classifier: Programming Language :: Python
Classifier: Programming Language :: Python :: 3.7
Classifier: Programming Language :: Python :: 3.8
Classifier: Programming Language :: Python :: 3.9
Classifier: Topic :: Software Development :: Libraries :: Python Modules
Requires-Python: ~=3.7
License-File: LICENSE.md
